os_tests/__init__.py
os_tests/os_tests_run.py
os_tests/cfg/alicloud.yaml
os_tests/cfg/aws.yaml
os_tests/cfg/azure.yaml
os_tests/cfg/google.yaml
os_tests/cfg/libvirt.yaml
os_tests/cfg/nutanix.yaml
os_tests/cfg/openshift.yaml
os_tests/cfg/openstack.yaml
os_tests/cfg/os-tests.yaml
os_tests/data/baseline_log.json
os_tests/docs/os-tests_advanced_tips.md
os_tests/libs/__init__.py
os_tests/libs/html_runner.py
os_tests/libs/resources.py
os_tests/libs/resources_alicloud.py
os_tests/libs/resources_aws.py
os_tests/libs/resources_azure.py
os_tests/libs/resources_gcp.py
os_tests/libs/resources_libvirt.py
os_tests/libs/resources_nutanix.py
os_tests/libs/resources_openshift.py
os_tests/libs/resources_openstack.py
os_tests/libs/utils_lib.py
os_tests/libs/version_util.py
os_tests/templates/sum.html
os_tests/templates/sum.xml
os_tests/tests/__init__.py
os_tests/tests/test_azure_image.py
os_tests/tests/test_azure_upgrade_check.py
os_tests/tests/test_cloud_init.py
os_tests/tests/test_gcp_image.py
os_tests/tests/test_general_check.py
os_tests/tests/test_general_test.py
os_tests/tests/test_image_mode.py
os_tests/tests/test_kickstart_install.py
os_tests/tests/test_lifecycle.py
os_tests/tests/test_ltp.py
os_tests/tests/test_network_test.py
os_tests/tests/test_nutanix_vm.py
os_tests/tests/test_rhel_cert.py
os_tests/tests/test_rhel_guest_image.py
os_tests/tests/test_storage.py
os_tests/tests/test_update.py
os_tests/tests/test_vtpm.py
os_tests/utils/blktests-master.aarch64.rpm
os_tests/utils/blktests-master.x86_64.rpm
os_tests/utils/debug_enable_user_with_passwd.sh
os_tests/utils/debug_nm_cloud_setup.sh
os_tests/utils/ltp-master.aarch64.rpm
os_tests/utils/ltp-master.x86_64.rpm
os_tests/utils/monitor_download_s3.py
os_tests/utils/nm_cloud_setup.sh
os_tests/utils/nw_pktgen.sh
os_tests/utils/redis_8124.c
os_tests/utils/systemd_analyze_services.sh
os_tests/utils/veth_nic_rx.sh
os_tests-0.4.0.dist-info/LICENSE
os_tests-0.4.0.dist-info/METADATA
os_tests-0.4.0.dist-info/WHEEL
os_tests-0.4.0.dist-info/entry_points.txt
os_tests-0.4.0.dist-info/top_level.txt
os_tests-0.4.0.dist-info/RECORD
