Metadata-Version: 2.1
Name: os-tests
Version: 0.4.0
Summary: Lightweight, portable and customer centric tests collection for Linux OS
Home-page: https://github.com/virt-s1/os-tests
Author: Xiao Liang
Author-email: xiliang@redhat.com
License: GPLv3+
Classifier: License :: OSI Approved :: GNU General Public License v3 or later (GPLv3+)
Classifier: Programming Language :: Python :: 3
Classifier: Operating System :: POSIX
Requires-Python: >=3.6
License-File: LICENSE
Requires-Dist: PyYAML
Requires-Dist: Jinja2 <=2.11.3
Requires-Dist: tipset >=0.2.4
Requires-Dist: markupsafe <=1.1.1
Requires-Dist: packaging <=21.3
